magma_indonesia/__init__.py
magma_indonesia/cli.py
magma_indonesia/dependencies.py
magma_indonesia/main.py
magma_indonesia/commands/__init__.py
magma_indonesia/commands/convert.py
magma_indonesia/commands/database.py
magma_indonesia/commands/db.py
magma_indonesia/commands/helper.py
magma_indonesia/commands/run.py
magma_indonesia/routers/__init__.py
magma_indonesia/routers/router.py
magma_indonesia/routers/websocket.py
magma_indonesia/routers/v1/__init__.py
magma_indonesia/routers/v1/seismic_router.py
magma_indonesia/static/__init__.py
magma_indonesia-0.0.3.dist-info/entry_points.txt
magma_indonesia-0.0.3.dist-info/licenses/LICENSE
magma_indonesia-0.0.3.dist-info/WHEEL
magma_indonesia-0.0.3.dist-info/METADATA
magma_indonesia-0.0.3.dist-info/RECORD
